{
  "navigationItems": [
    {
      "id": "1761724945457",
      "title": "媒体资讯",
      "icon": "Coffee",
      "description": "",
      "enabled": true,
      "items": [],
      "subCategories": []
    },
    {
      "id": "9",
      "title": "AI工具包",
      "icon": "Brain",
      "items": [],
      "subCategories": [
        {
          "id": "cbb3e33d-408b-41ba-9e9a-e0444303e3fd",
          "title": "AI助手",
          "icon": "Book",
          "description": "",
          "enabled": true,
          "items": []
        },
        {
          "id": "cbb3e33d-408b-41ba-9e9a-e0444303e3ff",
          "title": "生产力工具",
          "icon": "Book",
          "description": "",
          "enabled": true,
          "items": []
        },
        {
          "id": "21bf96f3-acb0-4e28-aaa8-2759ac55d278",
          "title": "MCP Server",
          "icon": "Edit",
          "description": "",
          "enabled": true,
          "items": []
        },
        {
          "id": "428d0ba1-78f8-48d6-83db-f837f3830e1f",
          "title": "多媒体",
          "icon": "BookOpen",
          "description": "",
          "enabled": true,
          "items": []
        },
        {
          "id": "eb656a11-5442-4670-9cb6-9ba9bd08682f",
          "title": "AI 代码生成助手",
          "icon": "Book",
          "description": "",
          "enabled": true,
          "items": []
        },
        {
          "id": "8f5e0374-2ee9-4012-acac-baecb515d826",
          "title": "提示词助手",
          "icon": "Book",
          "description": "",
          "enabled": true,
          "items": []
        }
      ],
      "description": "",
      "enabled": true
    }
  ]
}